m269_marking_plugin/__init__.py
m269_marking_plugin/_version.py
m269_marking_plugin-0.1.1.data/data/share/jupyter/labextensions/m269_marking_plugin/build_log.json
m269_marking_plugin-0.1.1.data/data/share/jupyter/labextensions/m269_marking_plugin/install.json
m269_marking_plugin-0.1.1.data/data/share/jupyter/labextensions/m269_marking_plugin/package.json
m269_marking_plugin-0.1.1.data/data/share/jupyter/labextensions/m269_marking_plugin/static/lib_index_js.5fbbb161d977128a3f21.js
m269_marking_plugin-0.1.1.data/data/share/jupyter/labextensions/m269_marking_plugin/static/lib_index_js.5fbbb161d977128a3f21.js.map
m269_marking_plugin-0.1.1.data/data/share/jupyter/labextensions/m269_marking_plugin/static/remoteEntry.efa0e46dc1dc43988faf.js
m269_marking_plugin-0.1.1.data/data/share/jupyter/labextensions/m269_marking_plugin/static/remoteEntry.efa0e46dc1dc43988faf.js.map
m269_marking_plugin-0.1.1.data/data/share/jupyter/labextensions/m269_marking_plugin/static/style.js
m269_marking_plugin-0.1.1.data/data/share/jupyter/labextensions/m269_marking_plugin/static/style_index_js.6565fe1c23365879d57f.js
m269_marking_plugin-0.1.1.data/data/share/jupyter/labextensions/m269_marking_plugin/static/style_index_js.6565fe1c23365879d57f.js.map
m269_marking_plugin-0.1.1.data/data/share/jupyter/labextensions/m269_marking_plugin/install.json
m269_marking_plugin-0.1.1.dist-info/METADATA
m269_marking_plugin-0.1.1.dist-info/WHEEL
m269_marking_plugin-0.1.1.dist-info/licenses/LICENSE
m269_marking_plugin-0.1.1.dist-info/RECORD
