Metadata-Version: 2.3
Name: m269_marking_plugin
Version: 0.1.1
Summary: Marking plugin for the M269 Open University module
Project-URL: Homepage, https://github.com/dsa-ou/m269_marking_plugin
Project-URL: Bug Tracker, https://github.com/dsa-ou/m269_marking_plugin/issues
Project-URL: Repository, https://github.com/dsa-ou/m269_marking_plugin.git
Author-email: Oli Howson <oli.howson@open.ac.uk>
License: BSD 3-Clause License
License-File: LICENSE
Keywords: jupyter,jupyterlab,jupyterlab-extension
Classifier: Framework :: Jupyter
Classifier: Framework :: Jupyter :: JupyterLab
Classifier: Framework :: Jupyter :: JupyterLab :: 4
Classifier: Framework :: Jupyter :: JupyterLab :: Extensions
Classifier: Framework :: Jupyter :: JupyterLab :: Extensions :: Prebuilt
Classifier: License :: OSI Approved :: BSD License
Classifier: Programming Language :: Python
Classifier: Programming Language :: Python :: 3
Classifier: Programming Language :: Python :: 3.8
Classifier: Programming Language :: Python :: 3.9
Classifier: Programming Language :: Python :: 3.10
Classifier: Programming Language :: Python :: 3.11
Classifier: Programming Language :: Python :: 3.12
Requires-Python: >=3.8
